.flake8
.gitignore
LICENSE.txt
MANIFEST.in
README.rst
publish.md
setup.cfg
setup.py
jwt_auth/__init__.py
jwt_auth/admin.py
jwt_auth/apps.py
jwt_auth/authentication.py
jwt_auth/init_fixtures.json
jwt_auth/models.py
jwt_auth/permissions.py
jwt_auth/serializers.py
jwt_auth/settings.py
jwt_auth/urls.py
jwt_auth/views.py
jwt_auth.egg-info/PKG-INFO
jwt_auth.egg-info/SOURCES.txt
jwt_auth.egg-info/dependency_links.txt
jwt_auth.egg-info/requires.txt
jwt_auth.egg-info/top_level.txt
jwt_auth.egg-info/zip-safe
jwt_auth/migrations/0001_initial.py
jwt_auth/migrations/__init__.py
jwt_auth/tests/__init__.py
jwt_auth/tests/conftest.py
jwt_auth/tests/test_views.py
jwt_auth/tests/urls.py
jwt_auth/tests/.cache/v/cache/lastfailed
requirements/testing.txt