Metadata-Version: 1.0
Name: jwt-auth
Version: 0.4.3
Summary: The JWT AUTH API
Home-page: https://github.com/CoinLQ/jwt_auth
Author: Xiandian
Author-email: lvpython@gmail.com
License: MIT
Platform: UNKNOWN
